{"1":{"h":[[1,1,"Abishag Cares for David"],[5,1,"Adonijah Usurps the Kingdom"],[11,1,"Nathan and Bathsheba before David"],[28,1,"David Renews His Oath to Bathsheba"],[32,1,"Solomon Anointed King"],[41,1,"Adonijah Learns of Solomon’s Kingship"]]},"2":{"h":[[1,1,"David Instructs Solomon"],[10,1,"David’s Reign and Death"],[13,1,"The Execution of Adonijah"],[28,1,"The Execution of Joab"],[36,1,"The Execution of Shimei"]]},"3":{"h":[[1,1,"Solomon’s Prayer for Wisdom"],[16,1,"Solomon Judges Wisely"]]},"4":{"h":[[1,1,"Solomon’s Princes"],[7,1,"Solomon’s Twelve Officers"],[20,1,"Solomon’s Prosperity"],[29,1,"Solomon’s Wisdom"]]},"5":{"h":[[1,1,"Preparations for the Temple"],[7,1,"Hiram’s Reply to Solomon"],[13,1,"Solomon’s Labor Force"]]},"6":{"h":[[1,1,"Temple Construction Begins"],[5,1,"The Chambers"],[11,1,"God’s Promise to Solomon"],[14,1,"The Temple’s Interior"],[23,1,"The Cherubim"],[31,1,"The Doors"],[36,1,"The Courtyard"]]},"7":{"h":[[1,1,"Solomon’s Palace Complex"],[13,1,"The Pillars and Capitals"],[23,1,"The Molten Sea"],[27,1,"The Ten Bronze Stands"],[38,1,"The Ten Bronze Basins"],[40,1,"Completion of the Bronze Works"],[48,1,"Completion of the Gold Furnishings"]]},"8":{"h":[[1,1,"The Ark Enters the Temple"],[12,1,"Solomon Blesses the LORD"],[22,1,"Solomon’s Prayer of Dedication"],[54,1,"Solomon’s Benediction"],[62,1,"Sacrifices of Dedication"]]},"9":{"h":[[1,1,"The LORD’s Response to Solomon"],[10,1,"Solomon’s Additional Achievements"]]},"10":{"h":[[1,1,"The Queen of Sheba"],[14,1,"Solomon’s Wealth and Splendor"]]},"11":{"h":[[1,1,"Solomon’s Foreign Wives"],[9,1,"God’s Anger against Solomon"],[14,1,"Hadad’s Return"],[23,1,"Rezon’s Hostility"],[26,1,"Jeroboam’s Rebellion"],[41,1,"The Death of Solomon"]]},"12":{"h":[[1,1,"Rebellion against Rehoboam"],[16,1,"The Kingdom Divided"],[20,1,"Shemaiah’s Prophecy"],[25,1,"Jeroboam’s Idolatry"]]},"13":{"h":[[1,1,"Jeroboam’s Hand Withers"],[11,1,"The Old Prophet and the Man of God"]]},"14":{"h":[[1,1,"Ahijah’s Prophecy against Jeroboam"],[19,1,"Nadab Succeeds Jeroboam"],[21,1,"Rehoboam Reigns in Judah"],[25,1,"Shishak Raids Jerusalem"]]},"15":{"h":[[1,1,"Abijam Reigns in Judah"],[9,1,"Asa Reigns in Judah"],[16,1,"War between Asa and Baasha"],[23,1,"Jehoshaphat Succeeds Asa"],[25,1,"Nadab Reigns in Israel"],[33,1,"Baasha Reigns in Israel"]]},"16":{"h":[[1,1,"Jehu’s Prophecy against Baasha"],[8,1,"Elah Reigns in Israel"],[15,1,"Zimri Reigns in Israel"],[21,1,"Omri Reigns in Israel"],[29,1,"Ahab Reigns in Israel, Marries Jezebel"]]},"17":{"h":[[1,1,"The Ravens Feed Elijah"],[8,1,"The Widow of Zarephath"],[17,1,"Elijah Raises the Widow’s Son"]]},"18":{"h":[[1,1,"Elijah’s Message to Ahab"],[16,1,"Elijah on Mount Carmel"],[36,1,"Elijah’s Prayer"],[41,1,"The LORD Sends Rain"]]},"19":{"h":[[1,1,"Elijah Flees from Jezebel"],[9,1,"The LORD Speaks to Elijah at Horeb"],[19,1,"The Call of Elisha"]]},"20":{"h":[[1,1,"Ben-hadad Attacks Samaria"],[13,1,"Ahab Defeats Ben-hadad"],[26,1,"Another War with Ben-hadad"],[31,1,"Ahab Spares Ben-hadad"],[35,1,"A Prophet Reproves Ahab"]]},"21":{"h":[[1,1,"Naboth’s Vineyard"],[8,1,"Jezebel’s Plot"],[17,1,"Elijah Denounces Ahab and Jezebel"],[25,1,"Ahab’s Repentance"]]},"22":{"h":[[1,1,"Ahab and the False Prophets"],[13,1,"Micaiah Prophesies against Ahab"],[29,1,"Ahab’s Defeat and Death"],[41,1,"Jehoshaphat Reigns in Judah"],[51,1,"Ahaziah Reigns in Israel"]]}}